LICENSE.txt
README.md
setup.cfg
setup.py
qeplot/BibTeX.dat
qeplot/DOI.png
qeplot/VASProcar.py
qeplot/__init__.py
qeplot/__main__.py
qeplot.egg-info/PKG-INFO
qeplot.egg-info/SOURCES.txt
qeplot.egg-info/dependency_links.txt
qeplot.egg-info/requires.txt
qeplot.egg-info/top_level.txt
qeplot/src/_grace_settings.py
qeplot/src/_loop.py
qeplot/src/_settings.py
qeplot/src/_update.py
qeplot/src/bandas_2D.py
qeplot/src/bandas_3D.py
qeplot/src/bandas_4D.py
qeplot/src/contribuicao.py
qeplot/src/correction_file.py
qeplot/src/fermi_surface.py
qeplot/src/level_countour.py
qeplot/src/projecao_localizacao.py
qeplot/src/projecao_orbitais.py
qeplot/src/projecao_psi.py
qeplot/src/projecao_spin.py
qeplot/src/spin_texture.py
qeplot/src/spin_texture_contour.py
qeplot/src/spin_texture_contour_video.py
qeplot/src/_QE/_info.py
qeplot/src/_QE/_info_b.py
qeplot/src/_QE/_label.py
qeplot/src/_QE/_nscf.py
qeplot/src/_QE/_var_kpoints.py
qeplot/src/_QE/dos_pdos_ldos.py
qeplot/src/_VASP/_info.py
qeplot/src/_VASP/_info_b.py
qeplot/src/_VASP/_label.py
qeplot/src/_VASP/_nscf.py
qeplot/src/_VASP/_var_kpoints.py
qeplot/src/_VASP/dielectric_function.py
qeplot/src/_VASP/dos_pdos_ldos.py
qeplot/src/_VASP/dos_pdos_ldos_[polarizado].py
qeplot/src/_VASP/kpoints_2D_3D.py
qeplot/src/_VASP/parchg.py
qeplot/src/_VASP/potencial.py
qeplot/src/_VASP/wave_function.py
qeplot/src/etc/BibTeX.dat
qeplot/src/etc/DOI.png
qeplot/src/etc/Greek_alphabet.jpg
qeplot/src/plot/plot_bandas_2D.py
qeplot/src/plot/plot_bandas_3D_matplotlib.py
qeplot/src/plot/plot_bandas_3D_plotly.py
qeplot/src/plot/plot_bandas_4D_plotly.py
qeplot/src/plot/plot_dielectric_function.py
qeplot/src/plot/plot_dos_pdos_ldos.py
qeplot/src/plot/plot_dos_pdos_ldos_[polarizado].py
qeplot/src/plot/plot_fermi_surface.py
qeplot/src/plot/plot_level_countour.py
qeplot/src/plot/plot_parchg.py
qeplot/src/plot/plot_potencial.py
qeplot/src/plot/plot_projecao_localizacao.py
qeplot/src/plot/plot_projecao_orbitais.py
qeplot/src/plot/plot_projecao_psi.py
qeplot/src/plot/plot_projecao_spin.py
qeplot/src/plot/plot_spin_texture_2D.py
qeplot/src/plot/plot_spin_texture_3D.py
qeplot/src/plot/plot_spin_texture_4D.py
