Metadata-Version: 2.1
Name: qeplot
Version: 1.0.7
Summary: VASProcar is an open-source package written in the Python 3 programming language, which aims to provide an intuitive tool for the post-processing of the output files produced by the DFT VASP code, through an interactive user interface.
Home-page: https://doi.org/10.5281/zenodo.6343960
Download-URL: https://doi.org/10.5281/zenodo.6343960
Author: Augusto de Lelis Araujo and Renan da Paixao Maciel
Author-email: augusto-lelis@outlook.com, renan.maciel@physics.uu.se
License: GNU GPLv3
License-File: LICENSE.txt
